chaoshen_winner_mcp_demo/__init__.py
chaoshen_winner_mcp_demo-0.1.0.dist-info/METADATA
chaoshen_winner_mcp_demo-0.1.0.dist-info/WHEEL
chaoshen_winner_mcp_demo-0.1.0.dist-info/entry_points.txt
chaoshen_winner_mcp_demo-0.1.0.dist-info/RECORD
